LICENSE
setup.py
tests/test_example.py
woodcut/__init__.py
woodcut/project.py
woodcut.egg-info/PKG-INFO
woodcut.egg-info/SOURCES.txt
woodcut.egg-info/dependency_links.txt
woodcut.egg-info/entry_points.txt
woodcut.egg-info/requires.txt
woodcut.egg-info/top_level.txt