Metadata-Version: 2.1
Name: woodcut
Version: 0.6.0
Summary: Minimalist content management system for static websites.
Home-page: http://wiki.github.com/lukecyca/woodcut
Author: Luke Cyca
Author-email: me@lukecyca.com
License: MIT
Keywords: mako template static web development
Classifier: Programming Language :: Python
Classifier: Programming Language :: Python :: 3.11
Classifier: License :: OSI Approved :: BSD License
Classifier: Operating System :: OS Independent
Classifier: Development Status :: 4 - Beta
Classifier: Natural Language :: English
Classifier: Topic :: Internet :: WWW/HTTP :: Site Management
Classifier: Topic :: Text Processing :: Markup
License-File: LICENSE
